hadronic/__init__.py
hadronic/core/__init__.py
hadronic/core/cli.py
hadronic/core/config.py
hadronic/hadron/__init__.py
hadronic/hadron/hadron.py
hadronic/hadron/tests.py
hadronic/hadron/workspace/__init__.py
hadronic/hadron/workspace/config.py
hadronic/hadron/workspace/fibonacci.py
hadronic-0.0.3.dist-info/METADATA
hadronic-0.0.3.dist-info/WHEEL
hadronic-0.0.3.dist-info/entry_points.txt
hadronic-0.0.3.dist-info/top_level.txt
hadronic-0.0.3.dist-info/RECORD
