Metadata-Version: 2.1
Name: hadronic
Version: 0.0.3
Author: Hammad Saeed
Author-email: hammad@supportvectors.com
Requires-Python: >=3.8
Requires-Dist: zyx
Requires-Dist: litellm
